{"data":{"finnish":{"path":"/405","title":"Better than Angels, Moses & Joshua","display":"block","bookName":"Hebrews","ref":"1:1-4:13","html":"<p></p>","questionsTitle":"QUESTIONS, QUESTIONS, QUESTIONS","Question1":"List all the many questions raised in this passage. Who makes them? To whom are they made?","Question2":"Is there a question that impacts you more than others? Why?","Question3":"What questions would do you have about issues raised in this passage?","Question4":"What can you do to get some answers to these questions you have raised?","prevPath":"/404","nextPath":"/406"}},"pageContext":{}}